03-FSM_pattrecon/FSM_moore.v
// Module-based representation of the pattern recognition FSM, adhering the Moore architectural principles. 

// Define the inputs and outputs
module FSM(
	input logic clk, // Clock, modelled to tick at a frequency of 100000Hz.  
	input logic s, // Serial input bus, feeding in the bits to the combinational logic. 
	input logic rst, // Active low reset pin. 
	
	output logic z // Pattern output flag
	);
	
	logic q2, q1, q0; // Define the current state bits. 
	logic q2n, q1n, q0n; // Define the next state bits (serves as a representatation of the 3 D-type flip flops.  
	
	// Denote the combinational logic to transition accordingly to the next state. 
	always_comb
	begin 
		q2n = (q2 & ~q0 & (~(s ^ q1))) | (q0 & s & (q2 ^ q1));
		q1n = (q1 & ~q0 & (q2 ^ s)) | (q0 & (~(q2 ^ s)));
		q0n = (~q2 & ~q0 & s) | (q2 & ~q1 & ~q0) | (~q2 & ~q1 & s);
		z = q2 & q1;
	end
	
	// Define the synchronous logic to synchronise the positive edge of the clock with flip flop state updates. 
	always_ff@(posedge clk)
	begin 
		if (!rst)
		begin
			q2 <= 0;
			q1 <= 0;
			q0 <= 0;
		end
		else 
		begin 
			q2 <= q2n;
			q1 <= q1n;
			q0 <= q0n;
		end
	end
endmodule

03-FSM_pattrecon/FSM_moore_tb.v
// Testbench to virtually prototype and validate a pattern recognition FSM of the following sequence: 101101. 

// Configure the timescale and max waveform resolution. 
`timescale 1ns / 1ps

module FSM_tb ();
	
	logic rst;
	logic clk;
	logic s;
	logic z;

	// Instantiate the module and cross-reference input and output ports with simulation ports
	FSM uut(
		.rst(rst),
		.clk(clk),
		.s(s),
		.z(z)
		);
	// Generate a waveform file for simulation purposes, and batch-load it with acquired testbench data for visualisation and debugging. 
	initial begin
		$dumpfile("FSM_pattrecon.vcd");
		$dumpvars(0, FSM_tb);
	end
	
	// Define a master clock rate of 100000Hz
	
	always #5000 clk = ~clk;
	
	// Initialise the testbench and control the simulation
	initial begin
		// Clear the reset, clock and s pins.
		clk <= 1'b0;
		rst <= 1'b0;
		s <= 1'b0;
		
		// After two clock cycles, pull the active low reset high to activate the flip flops. 
		repeat(2) @(posedge clk);
		rst <= 1'b1;
		
		// Background Monitor: This will print the counter value denoting the current state as well as whether the 'z' flag is high or not. 
                $monitor("[%0t] z=%b | s=%b q2=%b q1=%b q0=%b",
                $time, z, s, uut.q2, uut.q1, uut.q0);
		
		// Pattern recognition sequence testing and pattern failure mode state transition testing. 
		
		// S0 >> S1 (Input a 1; PATTERN-COMPLIANT)
		s <=  1'b1;
		@(posedge clk);
		#1; // Delay, to ensure that q2, q1 and q0 settle before next input. 
		
		// S1 >> S1 (Input 1; PATTERN NON-COMPLIANT)
		s <= 1'b1;
		@(posedge clk);
		#1;
		
		// S1 >> S2 (Input 0; PATTERN-COMPLIANT)
		s <= 1'b0;
                @(posedge clk);
                #1;
		
		// S2 >> S0 (Input 0; PATTERN NON-COMPLIANT)
		s <= 1'b0;
                @(posedge clk);
                #1;

		// S0 >> S1 (Input a 1; PATTERN-COMPLIANT)
                s <=  1'b1;
                @(posedge clk);
                #1;
		
		// S1 >> S2 (Input 0; PATTERN-COMPLIANT)
                s <= 1'b0;
                @(posedge clk);
                #1;
		
		// S2 >> S3 (Input 1; PATTERN-COMPLIANT)
                s <= 1'b1;
                @(posedge clk);
                #1;

		// S3 >> S2 (Input 0; PATTERN NON-COMPLIANT)
                s <= 1'b0;
                @(posedge clk);
                #1;

		// S2 >> S3 (Input 1; PATTERN-COMPLIANT)
                s <= 1'b1;
                @(posedge clk);
                #1;

		// S3 >> S4 (Input 1; PATTERN-COMPLIANT)
                s <= 1'b1;
                @(posedge clk);
                #1;

		// S4 >> S1 (Input 1; PATTERN NON-COMPLIANT)
                s <= 1'b1;
                @(posedge clk);
                #1;
		
		// S1 >> S2 (Input 0; PATTERN-COMPLIANT)
                s <= 1'b0;
                @(posedge clk);
                #1;
		
		// S2 >> S3 (Input 1; PATTERN-COMPLIANT)
                s <= 1'b1;
                @(posedge clk);
                #1;

		// S3 >> S4 (Input 1; PATTERN-COMPLIANT)
                s <= 1'b1;
                @(posedge clk);
                #1;
		
		// S4 >> S5 (Input 0; PATTERN-COMPLIANT)
                s <= 1'b0;
                @(posedge clk);
                #1;

		// S5 >> S0 (Input 0; PATTERN NON-COMPLIANT)
                s <= 1'b0;
                @(posedge clk);
                #1;

		// S0 >> S1 (Input 1; PATTERN-COMPLIANT)
                s <= 1'b1;
                @(posedge clk);
                #1;
		
		// S1 >> S2 (Input 0; PATTERN-COMPLIANT)
                s <= 1'b0;
                @(posedge clk);
                #1;

                // S2 >> S3 (Input 1; PATTERN-COMPLIANT)
                s <= 1'b1;
                @(posedge clk);
                #1;

                // S3 >> S4 (Input 1; PATTERN-COMPLIANT)
                s <= 1'b1;
                @(posedge clk);
                #1;

                // S4 >> S5 (Input 0; PATTERN-COMPLIANT)
                s <= 1'b0;
                @(posedge clk);
                #1;
		
		// S5 >> S6 (Input 1; PATTERN-COMPLIANT)
                s <= 1'b1;
                @(posedge clk);
                #1;
		
		// S6 >> S4 (Input 1; PATTERN NON-COMPLIANT)
                s <= 1'b1;
                @(posedge clk);
                #1;

		// S4 >> S5 (Input 0; PATTERN-COMPLIANT)
                s <= 1'b0;
                @(posedge clk);
                #1;

                // S5 >> S6 (Input 1; PATTERN-COMPLIANT)
                s <= 1'b1;
                @(posedge clk);
                #1;

		// S6 >> S2 (Input 0; PATTERN NON-COMPLIANT)
                s <= 1'b0;
                @(posedge clk);
                #1;

		$finish;
	end
endmodule

03-FSM_pattrecon/FSM_pattrecon.vcd
$date
	Sun Jul  5 21:23:13 2026
$end
$version
	Icarus Verilog
$end
$timescale
	1ps
$end
$scope module FSM_tb $end
$var wire 1 ! z $end
$var reg 1 " clk $end
$var reg 1 # rst $end
$var reg 1 $ s $end
$scope module uut $end
$var wire 1 " clk $end
$var wire 1 # rst $end
$var wire 1 $ s $end
$var reg 1 % q0 $end
$var reg 1 & q0n $end
$var reg 1 ' q1 $end
$var reg 1 ( q1n $end
$var reg 1 ) q2 $end
$var reg 1 * q2n $end
$var reg 1 ! z $end
$upscope $end
$upscope $end
$enddefinitions $end
$comment Show the parameter values. $end
$dumpall
$end
#0
$dumpvars
x*
x)
x(
x'
x&
x%
0$
0#
0"
x!
$end
#5000000
0!
0&
0(
0*
0%
0'
0)
1"
#10000000
0"
#15000000
1&
1$
1#
1"
#20000000
0"
#25000000
1%
1"
#30000000
0"
#35000000
1"
#35001000
0&
1(
0$
#40000000
0"
#45000000
0(
0%
1'
1"
#50000000
0"
#55000000
0'
1"
#55001000
1&
1$
#60000000
0"
#65000000
1%
1"
#65001000
0&
1(
0$
#70000000
0"
#75000000
0(
0%
1'
1"
#75001000
1&
1(
1$
#80000000
0"
#85000000
0&
0(
1*
1%
1"
#85001000
1(
0*
0$
#90000000
0"
#95000000
0(
0%
1"
#95001000
1&
1(
1$
#100000000
0"
#105000000
0&
0(
1*
1%
1"
#110000000
0"
#115000000
1&
0*
0%
0'
1)
1"
#120000000
0"
#125000000
1%
0)
1"
#125001000
0&
1(
0$
#130000000
0"
#135000000
0(
0%
1'
1"
#135001000
1&
1(
1$
#140000000
0"
#145000000
0&
0(
1*
1%
1"
#150000000
0"
#155000000
1&
0*
0%
0'
1)
1"
#155001000
1*
0$
#160000000
0"
#165000000
0&
0*
1%
1"
#170000000
0"
#175000000
0%
0)
1"
#175001000
1&
1$
#180000000
0"
#185000000
1%
1"
#185001000
0&
1(
0$
#190000000
0"
#195000000
0(
0%
1'
1"
#195001000
1&
1(
1$
#200000000
0"
#205000000
0&
0(
1*
1%
1"
#210000000
0"
#215000000
1&
0*
0%
0'
1)
1"
#215001000
1*
0$
#220000000
0"
#225000000
0&
0*
1%
1"
#225001000
1(
1*
1$
#230000000
0"
#235000000
1!
0(
0%
1'
1"
#240000000
0"
#245000000
0!
1&
0*
0'
1"
#245001000
1*
0$
#250000000
0"
#255000000
0&
0*
1%
1"
#255001000
1(
1*
1$
#260000000
0"
#265000000
1!
0(
0%
1'
1"
#265001000
1(
0*
0$
#270000000
0"
#275000000
0!
0(
0)
1"
