01-sync_fifo/sync_fifo_new.v
// Configure a synchronous FIFO to buffer IMU data between a ESP-32 CPU and a BLE peripheral. Refer to 'Sync_Fifo_explanation.odt' for added clarity and exhaustive list of instructions and design justification. 

// Configure the timescale 
`timescale 1ns / 1ps

// Configure externally-driven inputs and outputs within the module definition. Note that declarations of any internal elements must be declared further on - the module definition must only // contain potential input and output pins facing external components as opposed to every connection required within the FIFO. E.g. signals driven from the external CPU domain to the FIFO 
// must be denoted by input pins, whereas connections established between the write domain and the RAM block must not be initialised via input/output pins in the module definition section - // this risks accidental connections that may jeopardise the operation of the FIFO, and increases routing complexity (redundant wires that feeding externally must be plugged back into the   //  FIFO module, worsening the footprint of the entire module. 
module sync_fifo #(parameter DEPTH = 128, LENGTH = 48, DEPTHBIN = 7) // Declaring parameters (equivalent of variables) during the configuration of the module is standard programming practice                                                                     // to ensure traceability of variable values throughout the program, and a consistent digital record. Individually 
                                                                     // assigning values to any elements further down which share common parameters with other elements necessitates 
                                                                     // individually amending every single element's value, proving to be a tedious affair. Instead, an associated 'parameter'                                                                     //  value can be amended that propogates to every element assigned to that 'parameter'. 
	(
	input logic [LENGTH-1:0] d_in, // 48-bit parallel 'Data In' bus into the FIFO from the Arduino MCU. 
	input logic 	   rd_en, // Read enable pin that is hooked up directly to a digital output pin of the ESP-32 MCU. External logic to step down the read rate from 80MHz (ESP-32 Master                                  // Clock) to 1Hz (chosen read sampling rate) via a 27-bit counter that increments to 79999999 clock cycles @ 80MHz (representing 1 clock cycle @ 1Hz), with                                   // the 1Hz clock output connected directly to a 7-bit burst counter that executes 100 clock cycles @ 80MHz driven by the digital output pin from the ESP-32                                   // MCU. The digital output pin fires a high signal to the read enable pin of the FIFO every clock cycle increment for 100 cycles @ 80MHz to release the next                                  // data payload. 
	input logic 	   wr_en, // Write enable pin that is hooked up directly to a digital output pin of the ESP-32 MCU. External logic to step down the write rate from 80MHz (ESP-32                                       // Master Clock) to 100Hz (chosen write sampling rate) is nested within the ESP-32; the digital output pin fires a high signal to the write enable pin of                                     // the FIFO once a subsequent data payload has successfully been processed and refined. 
	input logic 	   clk, // 80MHz clock input into the FIFO for RAM block gating purposes; every attempted write/read is momentarily halted until the next positive clock edge from the                                // master. Prevents any settling errors in the pointers. 
	output logic [LENGTH-1:0]   d_out, // 48-bit parallel 'Data Out' bus running from the FIFO back to the Arduino MCU.
	output logic 		    full,  // A 'full' flag was deemed to be an appropriate pin, since this wire hooks up to the ESP-32's CPU to gate access of incoming payloads to the                                                 // 'd_in' bus. Without the 'full' flag configured as an output to the ESP-32, the CPU will continuously transmit data towards the the FIFO, despite                                           //  the access of certain payloads being gated by the 'full flag' into the RAM block. Since the 48-bit data bus contains zero storage capabilities,                                           //  unsuccessful payloads will be overwritten by the next payload initiated by the CPUs clock.  
	output logic 		    empty, // Similarly, an 'empty' flag was deemed necessary, to provide the CPU full control over alerting the FIFO when it is ready to catch the next 
                                           // payload of refined data during the 100-cycle burst period. If the 'empty' flag is not relayed back to the CPU despite remaining clock cycles
					   // within the burst period,repeated data will get pulled by the CPU inadvertendly. The inclusion of an 'empty' flag output alerts the CPU 
                                           // that the read and write pointers correspond to identical RAM wordlines, prompting the CPU to terminate the burst period prematurely.
	input logic		    reset_n, // Automatic 'active low' reset when glitches or malfunctions are detected in the CPU during an active session. Heavy loads require excessive
       	                                    // voltage drops that may minimise available power draw for the transistors within the RAM block. Insufficient gate voltages for the MOSFETs will 
					    // result in transistor switching
					    // failure, culminating in
					    // critical FIFO malfunctions. The
					    // 'active low' reset ensures that
					    // FIFO elements are rebooted by
					    // being pulled down to zero
					    // instead of pulled up, given
					    // insufficient power is received
					    // by the FIFO in the first place.
	output logic 		    wr_ack, // A write_acknowledge handshake alert, informing ESP-32's CPU that a write was successfully executed to the FIFO. If this alert does not get 
       					    // received, this indicates that the master clock connetion between the CPU and the RAM block is corrupted or blown altogether.
	output logic 		    rd_ack // Same working principle applies to the read acknowledge handshake. Since the master clock dictates the activation of cell transistors to release 						  // data during the burst sequence, if this acknowledge alert is not received by the CPU, this again implies a faulty connection between the RAM 						// block and the master clock. 	

	);
	
	// Configuration of interconnections internal to the FIFO, e.g. AND
	// gate routings, pointer declarations, etc. 
	logic [DEPTHBIN-1:0] rd_up; // The read pointer must be sized in accordance with the max payload capacity of the FIFO at any given point (128 states from the 7 bit counter is                                            // sufficient to monitor and trigger 100 uniquely addressed FIFO reads @ 1Hz).  
	logic [DEPTHBIN-1:0] wr_up; // The write pointer must be sized in accordance with the max payload capacity of the FIFO at any given point (128 states from the 7 bit counter is                                           // sufficient to monitor and trigger 100 uniquely addressed FIFO writes @ 100Hz).
	logic [LENGTH-1:0] fifo[0:DEPTH-1]; // The FIFO is configured with 100 wordlines and 48 bitlines (for each individual 6-byte data payload).
	logic [DEPTHBIN - 1:0] depth_diff; // Signed variable to calculate the difference between the write pointer and the read pointer. These enable negative numbers to be computed.
       					     //	Unsigned variables are configured with a range of 0-127, whereas signed spans from -127 to 127. The extra bit ensures that difference 
					     //	calculations always fall within range.  

	// Procedural description of the write and read domains in the FIFO
	always_ff @ (posedge clk)
	begin
		if (!reset_n) // The inversion of the reset variable fulfils an 'active low' approach to resetting the write and read domains. 
		begin
			wr_up <= 0; // Resets the write pointer to prevent any further transistor malfunctions. 
			rd_up <= 0; // Resets the read pointer to prevent any further transistor malfunctions. 
		end
		else 
		begin
			if (wr_en && !full)
			begin            	// Describing input conditions feeding into the write enable AND gate, culminating in a successful write to the RAM block. 
				fifo [wr_up] <= d_in; // The FIFO is indexed with the current pointer binary value (points towards the corresponding RAM wordline), and the current data 
						      // payload is written to
						      // this index. 
				wr_up <= wr_up + 1;   // The pointer increments by 1, in preparation for the next data payload input into the write domain. 
				wr_ack <= 1; // Signal to the ESP-32 that the FIFO has successfully received an incoming data payload.
			       	rd_ack <= 0; // The read acknowledge should not be activated unexpectedly (serves as belt and brace).	
			end
			else if (rd_en && !empty) // Describing input conditions feeding into the read enable AND gate, culminating in a successful read from the RAM block to the ESP CPU.  
			begin
				d_out <= fifo [rd_up]; // The FIFO is indexed with the current read pointer binary value, and is assigned to the 'd_out' output bus. 
				rd_up <= rd_up + 1; // The read pointer is incremented by 1, in preparation of grabbing the next wordline and outputting it during the burst period.
			        rd_ack <= 1; // Signal to the ESP-32 that the FIFO has successfully released a data payload during the burst sequence. 
				wr_ack <= 0; // The write acknowledge should remain low (serves as belt and brace).	
			end
			else 
			begin
				rd_ack <= 0; // In the event that the FIFO is awaiting a read/write enable signal, pull both acknowledge outputs down.
				wr_ack <= 0;
			end
		end
	end

	// Procedural combination logic denoting the depth counter and
	// configuring full and empty conditions. 
	always_comb
	begin 
	depth_diff = wr_up - rd_up; // Equate the depth counter value to the difference between the write pointer and the read pointer. 
		if (depth_diff == 7'd100) 
		begin
			full = 1; // If the current depth is 100, pull the full flag high.
			empty = 0;	
		end
		else if (depth_diff == 7'd0)
		begin	
			empty = 1; // If the current depth is 0., pull the empty flag high. 
			full = 0;
		end
		else
		begin 
			full = 0; 
			empty = 0; // Both the flags should be set low otherwise
		end
	end
endmodule

01-sync_fifo/sync_fifo_tb.v
// Testbench to prototype the functionalities of the synchronous FIFO to be embedded within the ESP-32 data pipeline of a smart removable insole. 

// Configure the timescale
`timescale 1ns / 1ps

// Configure the testbench module description
module sync_fifo_tb();
	// Declare the required input and output simulation pins. 
	logic [47:0]  d_out;
	logic [47:0]  d_in;
	logic 	      rd_en;
	logic 	      wr_en;
	logic 	      clk;
	logic 	      reset_n;
	logic         empty;
	logic         full;
	logic [47:0]  d_data;
	logic 	      wr_ack;
	logic 	      rd_ack;

	// Instantiate the module and cross-reference input and output ports with simulation ports. 
	sync_fifo uut (
		.d_out(d_out),
		.d_in(d_in),
		.rd_en(rd_en),
		.wr_en(wr_en),
		.clk(clk),
		.reset_n(reset_n),
		.empty(empty),
		.full(full),
		.wr_ack(wr_ack),
		.rd_ack(rd_ack)
		);
	// Create a waveform file for simulation purposes, and dump gathered testbench data for visualisation and debugging.
	initial begin
		$dumpfile("sync_fifo.vcd");
      		$dumpvars(0, sync_fifo_tb);
	end	
	// The master clock must tick at a frequency of 80MHz, which is equivalent to 6.25ns for half a period. 
	always
		#6.25 clk = ~clk;
	// Initialise the signals and control the simulation. 
 	initial begin
		// Clear enable and input/output pins. 
		d_data <= 48'b0;
		d_in <= 48'b0;
		rd_en <= 1'b0;
		wr_en <= 1'b0;
		reset_n <= 1'b0;
		clk <= 1'b0;
		
		// After 25 ns, activate the FIFO by pulling the reset pin up 
		#25 reset_n <= 1'b1;

		@(posedge clk);  // Data will only commence firing to the FIFO once the FIFO has locked onto a positive clock edge, to ensuring flawless timing. 
		
		// Background Monitor: This will print a line to the console anytime a critical signal changes
    		$monitor("[%0t] full=%b | wr_en=%b wr_up=%0d din=0x%0h | rd_en=%b rd_up=%0d dout=0x%0h", 
        	$time, full, wr_en, uut.wr_up, d_in, rd_en, uut.rd_up, d_out);

		// Initialise two independent write and read threads that function concurrently using the 'fork ....  join' block. 
		fork 
		begin 
			int timeout_counter;
			
			while (!full) // Runs when there is sufficient capacity within the RAM block, and the FIFO hasn't hit its 100 payload capacity yet. 
			begin 
				#100; // Throttled frequency of 100Hz (scaled for the purposes of this simulation) for writes. 
				@(posedge clk) // Ensures that the FIFO is ready to receive data, instead of risking pushing a payload mid-clock cycle and triggering metastability issues. 

				
				wr_en <= 1'b1; // The write enable gets pulled high; 
				d_in <= {$random, $random}; // Since '$random' can only generate a max of 32-bits in one single invocation, two separate '$random' functions must be 
							    // concatenated to reach 48-bits to store the full extent of an incoming payload.
				
				@(posedge clk);
				wr_en <= 1'b0;  // Pull up the write enable for exactly one cycle, to prevent the write pointer from incrementing again during the write acknowledgment 						// check. This cuts the max payload capacity in half and duplicates data unnecessarily in the FIFO.   
				 // Reset the timeout counter back to zero
				 timeout_counter = 0;

				 // The program freezes until a valid write acknowledgement is transmitted to the ESP-32 CPU. The clock ensures that the write acknowledgement is pushed
				 // before the while loop restarts to begin the next cycle @ 100Hz. 
				while (!wr_ack)
			      	begin 
					@(posedge clk);
					timeout_counter = timeout_counter + 1;
					if (timeout_counter > 5)
					begin 
						$display("Fatal write acknowledgment timeout from the FIFO!!");
						$stop;
					end

				end
				
			
				// The write enable drops low to prevent any garbage data payloads from registering on the FIFO before the nex clock cycle @ 100Hz. 
				wr_en <= 1'b0;

				// Wait another clock cycle for any pointers and flags within the hardware module to settle before jumping headfirst into the next iteration of the 
				// while loop - may result in full flags slipping through the cracks and causing timeout failures. 
				@(posedge clk);
			end
			$display("\n[%0t] WRITE THREAD HALTED: FIFO 'full' flag is HIGH. Hardware successfully blocked further writes.\n", $time);
		end
		

		begin 
			int timeout_counter1;

			wait(full == 1'b1); // Instead of cadencing the burst sequence every 1Hz, wait until the full flag is pulled up before beginning this. This mimics ESP32 interru				            // pt logic by tying the full pin direcly to the read domain logic. Depends on whether the intention is to pump out 100 payload every second					    // or wait until a 100 payloads have been received before streaming this to the smartphone.  
			@(posedge clk);

			$display("1Hz timer fired! Initiating burst read.");

			// Drain the FIFO until the hardware capacity until the hardware capacity explicitly states emptiness 
			while (!empty)
			begin 
				rd_en <= 1'b1;
				@(posedge clk);
				d_data <= d_out;
				
				// Reset the read timeout counter back to zero
				timeout_counter1 = 0;

				// The program freezes until a valid read acknowledgement is transmitted to the ESP-32. The clock ensured that the read acknowledgement is pushed before the 				      // while loop restarts to begin the next cycle @ 80Mhz.
				while (!rd_ack)
				begin 
					@(posedge clk);
					timeout_counter1 = timeout_counter1 + 1;
					if  (timeout_counter1 > 5)
					begin 
						$display("Fatal read acknowledgement timeout from the FIFO!!");
						$stop;
					end
				end
				
			end
			

			// Once the burst sequence is over, pull the read enable back down to 0.
			rd_en <= 1'b0;
			$display("Burst sequence has finished!!");
		end
		join

		#500 $finish; // Wait 500ns before terminating the testbench. 

	end
				
endmodule

01-sync_fifo/sync_fifo.vcd
$date
	Mon Jun 22 16:45:57 2026
$end
$version
	Icarus Verilog
$end
$timescale
	1ps
$end
$scope module sync_fifo_tb $end
$var wire 1 ! wr_ack $end
$var wire 1 " rd_ack $end
$var wire 1 # full $end
$var wire 1 $ empty $end
$var wire 48 % d_out [47:0] $end
$var reg 1 & clk $end
$var reg 48 ' d_data [47:0] $end
$var reg 48 ( d_in [47:0] $end
$var reg 1 ) rd_en $end
$var reg 1 * reset_n $end
$var reg 1 + wr_en $end
$scope module uut $end
$var wire 1 & clk $end
$var wire 48 , d_in [47:0] $end
$var wire 1 ) rd_en $end
$var wire 1 * reset_n $end
$var wire 1 + wr_en $end
$var parameter 32 - DEPTH $end
$var parameter 32 . DEPTHBIN $end
$var parameter 32 / LENGTH $end
$var reg 48 0 d_out [47:0] $end
$var reg 7 1 depth_diff [6:0] $end
$var reg 1 $ empty $end
$var reg 1 # full $end
$var reg 1 " rd_ack $end
$var reg 7 2 rd_up [6:0] $end
$var reg 1 ! wr_ack $end
$var reg 7 3 wr_up [6:0] $end
$upscope $end
$scope begin $unm_blk_14 $end
$var integer 32 4 timeout_counter [31:0] $end
$upscope $end
$scope begin $unm_blk_18 $end
$var integer 32 5 timeout_counter1 [31:0] $end
$upscope $end
$upscope $end
$enddefinitions $end
$comment Show the parameter values. $end
$dumpall
b110000 /
b111 .
b10000000 -
$end
#0
$dumpvars
b0 5
b0 4
bx 3
bx 2
bx 1
bx 0
b0 ,
0+
0*
0)
b0 (
b0 '
0&
bx %
0$
0#
x"
x!
$end
#6250
1$
b0 1
b0 2
b0 3
1&
#12500
0&
#18750
1&
#25000
1*
0&
#31250
0!
0"
1&
#37500
0&
#43750
1&
#50000
0&
#56250
1&
#62500
0&
#68750
1&
#75000
0&
#81250
1&
#87500
0&
#93750
1&
#100000
0&
#106250
1&
#112500
0&
#118750
1&
#125000
0&
#131250
b1101010010010011000000100010010101111010000001 (
b1101010010010011000000100010010101111010000001 ,
1+
1&
#137500
0&
#143750
0$
b1 1
0+
1!
b1 3
1&
#150000
0&
#156250
0!
b1 4
1&
#162500
0&
#168750
1&
#175000
0&
#181250
1&
#187500
0&
#193750
1&
#200000
0&
#206250
1&
#212500
0&
#218750
1&
#225000
0&
#231250
1&
#237500
0&
#243750
1&
#250000
0&
#256250
1&
#262500
0&
#268750
b110101100000100110110001111100000101011001100011 (
b110101100000100110110001111100000101011001100011 ,
1+
1&
#275000
0&
#281250
b10 1
0+
1!
b10 3
b0 4
1&
#287500
0&
#293750
0!
b1 4
1&
#300000
0&
#306250
1&
#312500
0&
#318750
1&
#325000
0&
#331250
1&
#337500
0&
#343750
1&
#350000
0&
#356250
1&
#362500
0&
#368750
1&
#375000
0&
#381250
1&
#387500
0&
#393750
1&
#400000
0&
#406250
b11110110000110101000110110111111001100110001101 (
b11110110000110101000110110111111001100110001101 ,
1+
1&
#412500
0&
#418750
b11 1
0+
1!
b11 3
b0 4
1&
#425000
0&
#431250
0!
b1 4
1&
#437500
0&
#443750
1&
#450000
0&
#456250
1&
#462500
0&
#468750
1&
#475000
0&
#481250
1&
#487500
0&
#493750
1&
#500000
0&
#506250
1&
#512500
0&
#518750
1&
#525000
0&
#531250
1&
#537500
0&
#543750
b100001000110010110001001001101110101001000010010 (
b100001000110010110001001001101110101001000010010 ,
1+
1&
#550000
0&
#556250
b100 1
0+
1!
b100 3
b0 4
1&
#562500
0&
#568750
0!
b1 4
1&
#575000
0&
#581250
1&
#587500
0&
#593750
1&
#600000
0&
#606250
1&
#612500
0&
#618750
1&
#625000
0&
#631250
1&
#637500
0&
#643750
1&
#650000
0&
#656250
1&
#662500
0&
#668750
1&
#675000
0&
#681250
b111000110000000100000110110101111100110100001101 (
b111000110000000100000110110101111100110100001101 ,
1+
1&
#687500
0&
#693750
b101 1
0+
1!
b101 3
b0 4
1&
#700000
0&
#706250
0!
b1 4
1&
#712500
0&
#718750
1&
#725000
0&
#731250
1&
#737500
0&
#743750
1&
#750000
0&
#756250
1&
#762500
0&
#768750
1&
#775000
0&
#781250
1&
#787500
0&
#793750
1&
#800000
0&
#806250
1&
#812500
0&
#818750
b111100010111011000011110100011011100110100111101 (
b111100010111011000011110100011011100110100111101 ,
1+
1&
#825000
0&
#831250
b110 1
0+
1!
b110 3
b0 4
1&
#837500
0&
#843750
0!
b1 4
1&
#850000
0&
#856250
1&
#862500
0&
#868750
1&
#875000
0&
#881250
1&
#887500
0&
#893750
1&
#900000
0&
#906250
1&
#912500
0&
#918750
1&
#925000
0&
#931250
1&
#937500
0&
#943750
1&
#950000
0&
#956250
b10101111110110101000110001011011111011110001100 (
b10101111110110101000110001011011111011110001100 ,
1+
1&
#962500
0&
#968750
b111 1
0+
1!
b111 3
b0 4
1&
#975000
0&
#981250
0!
b1 4
1&
#987500
0&
#993750
1&
#1000000
0&
#1006250
1&
#1012500
0&
#1018750
1&
#1025000
0&
#1031250
1&
#1037500
0&
#1043750
1&
#1050000
0&
#1056250
1&
#1062500
0&
#1068750
1&
#1075000
0&
#1081250
1&
#1087500
0&
#1093750
b111010011111100111100011001101110010010011000110 (
b111010011111100111100011001101110010010011000110 ,
1+
1&
#1100000
0&
#1106250
b1000 1
0+
1!
b1000 3
b0 4
1&
#1112500
0&
#1118750
0!
b1 4
1&
#1125000
0&
#1131250
1&
#1137500
0&
#1143750
1&
#1150000
0&
#1156250
1&
#1162500
0&
#1168750
1&
#1175000
0&
#1181250
1&
#1187500
0&
#1193750
1&
#1200000
0&
#1206250
1&
#1212500
0&
#1218750
1&
#1225000
0&
#1231250
b100001001100010111010101000100111101001010101010 (
b100001001100010111010101000100111101001010101010 ,
1+
1&
#1237500
0&
#1243750
b1001 1
0+
1!
b1001 3
b0 4
1&
#1250000
0&
#1256250
0!
b1 4
1&
#1262500
0&
#1268750
1&
#1275000
0&
#1281250
1&
#1287500
0&
#1293750
1&
#1300000
0&
#1306250
1&
#1312500
0&
#1318750
1&
#1325000
0&
#1331250
1&
#1337500
0&
#1343750
1&
#1350000
0&
#1356250
1&
#1362500
0&
#1368750
b111101111110010110111011110100100111001001110111 (
b111101111110010110111011110100100111001001110111 ,
1+
1&
#1375000
0&
#1381250
b1010 1
0+
1!
b1010 3
b0 4
1&
#1387500
0&
#1393750
0!
b1 4
1&
#1400000
0&
#1406250
1&
#1412500
0&
#1418750
1&
#1425000
0&
#1431250
1&
#1437500
0&
#1443750
1&
#1450000
0&
#1456250
1&
#1462500
0&
#1468750
1&
#1475000
0&
#1481250
1&
#1487500
0&
#1493750
1&
#1500000
0&
#1506250
b110101100001001001000111111011001101101110001111 (
b110101100001001001000111111011001101101110001111 ,
1+
1&
#1512500
0&
#1518750
b1011 1
0+
1!
b1011 3
b0 4
1&
#1525000
0&
#1531250
0!
b1 4
1&
#1537500
0&
#1543750
1&
#1550000
0&
#1556250
1&
#1562500
0&
#1568750
1&
#1575000
0&
#1581250
1&
#1587500
0&
#1593750
1&
#1600000
0&
#1606250
1&
#1612500
0&
#1618750
1&
#1625000
0&
#1631250
1&
#1637500
0&
#1643750
b11010011111001011100111011101101001011011001110 (
b11010011111001011100111011101101001011011001110 ,
1+
1&
#1650000
0&
#1656250
b1100 1
0+
1!
b1100 3
b0 4
1&
#1662500
0&
#1668750
0!
b1 4
1&
#1675000
0&
#1681250
1&
#1687500
0&
#1693750
1&
#1700000
0&
#1706250
1&
#1712500
0&
#1718750
1&
#1725000
0&
#1731250
1&
#1737500
0&
#1743750
1&
#1750000
0&
#1756250
1&
#1762500
0&
#1768750
1&
#1775000
0&
#1781250
b11110101110100011100010110010100100111011000101 (
b11110101110100011100010110010100100111011000101 ,
1+
1&
#1787500
0&
#1793750
b1101 1
0+
1!
b1101 3
b0 4
1&
#1800000
0&
#1806250
0!
b1 4
1&
#1812500
0&
#1818750
1&
#1825000
0&
#1831250
1&
#1837500
0&
#1843750
1&
#1850000
0&
#1856250
1&
#1862500
0&
#1868750
1&
#1875000
0&
#1881250
1&
#1887500
0&
#1893750
1&
#1900000
0&
#1906250
1&
#1912500
0&
#1918750
b10010010101110011011110100011100010100010111101 (
b10010010101110011011110100011100010100010111101 ,
1+
1&
#1925000
0&
#1931250
b1110 1
0+
1!
b1110 3
b0 4
1&
#1937500
0&
#1943750
0!
b1 4
1&
#1950000
0&
#1956250
1&
#1962500
0&
#1968750
1&
#1975000
0&
#1981250
1&
#1987500
0&
#1993750
1&
#2000000
0&
#2006250
1&
#2012500
0&
#2018750
1&
#2025000
0&
#2031250
1&
#2037500
0&
#2043750
1&
#2050000
0&
#2056250
b10110000010110110110010101001110010011001100101 (
b10110000010110110110010101001110010011001100101 ,
1+
1&
#2062500
0&
#2068750
b1111 1
0+
1!
b1111 3
b0 4
1&
#2075000
0&
#2081250
0!
b1 4
1&
#2087500
0&
#2093750
1&
#2100000
0&
#2106250
1&
#2112500
0&
#2118750
1&
#2125000
0&
#2131250
1&
#2137500
0&
#2143750
1&
#2150000
0&
#2156250
1&
#2162500
0&
#2168750
1&
#2175000
0&
#2181250
1&
#2187500
0&
#2193750
b11000100110001100000101011100111000011100001010 (
b11000100110001100000101011100111000011100001010 ,
1+
1&
#2200000
0&
#2206250
b10000 1
0+
1!
b10000 3
b0 4
1&
#2212500
0&
#2218750
0!
b1 4
1&
#2225000
0&
#2231250
1&
#2237500
0&
#2243750
1&
#2250000
0&
#2256250
1&
#2262500
0&
#2268750
1&
#2275000
0&
#2281250
1&
#2287500
0&
#2293750
1&
#2300000
0&
#2306250
1&
#2312500
0&
#2318750
1&
#2325000
0&
#2331250
b1000101000000000010000011001000010000100100000 (
b1000101000000000010000011001000010000100100000 ,
1+
1&
#2337500
0&
#2343750
b10001 1
0+
1!
b10001 3
b0 4
1&
#2350000
0&
#2356250
0!
b1 4
1&
#2362500
0&
#2368750
1&
#2375000
0&
#2381250
1&
#2387500
0&
#2393750
1&
#2400000
0&
#2406250
1&
#2412500
0&
#2418750
1&
#2425000
0&
#2431250
1&
#2437500
0&
#2443750
1&
#2450000
0&
#2456250
1&
#2462500
0&
#2468750
b10001011010101011001110110011001100110010011101 (
b10001011010101011001110110011001100110010011101 ,
1+
1&
#2475000
0&
#2481250
b10010 1
0+
1!
b10010 3
b0 4
1&
#2487500
0&
#2493750
0!
b1 4
1&
#2500000
0&
#2506250
1&
#2512500
0&
#2518750
1&
#2525000
0&
#2531250
1&
#2537500
0&
#2543750
1&
#2550000
0&
#2556250
1&
#2562500
0&
#2568750
1&
#2575000
0&
#2581250
1&
#2587500
0&
#2593750
1&
#2600000
0&
#2606250
b1111101001011010001001100000111011100000010011 (
b1111101001011010001001100000111011100000010011 ,
1+
1&
#2612500
0&
#2618750
b10011 1
0+
1!
b10011 3
b0 4
1&
#2625000
0&
#2631250
0!
b1 4
1&
#2637500
0&
#2643750
1&
#2650000
0&
#2656250
1&
#2662500
0&
#2668750
1&
#2675000
0&
#2681250
1&
#2687500
0&
#2693750
1&
#2700000
0&
#2706250
1&
#2712500
0&
#2718750
1&
#2725000
0&
#2731250
1&
#2737500
0&
#2743750
b1110000000110110101001101001111101011001010011 (
b1110000000110110101001101001111101011001010011 ,
1+
1&
#2750000
0&
#2756250
b10100 1
0+
1!
b10100 3
b0 4
1&
#2762500
0&
#2768750
0!
b1 4
1&
#2775000
0&
#2781250
1&
#2787500
0&
#2793750
1&
#2800000
0&
#2806250
1&
#2812500
0&
#2818750
1&
#2825000
0&
#2831250
1&
#2837500
0&
#2843750
1&
#2850000
0&
#2856250
1&
#2862500
0&
#2868750
1&
#2875000
0&
#2881250
b110111010110101111101010101001100010101011010101 (
b110111010110101111101010101001100010101011010101 ,
1+
1&
#2887500
0&
#2893750
b10101 1
0+
1!
b10101 3
b0 4
1&
#2900000
0&
#2906250
0!
b1 4
1&
#2912500
0&
#2918750
1&
#2925000
0&
#2931250
1&
#2937500
0&
#2943750
1&
#2950000
0&
#2956250
1&
#2962500
0&
#2968750
1&
#2975000
0&
#2981250
1&
#2987500
0&
#2993750
1&
#3000000
0&
#3006250
1&
#3012500
0&
#3018750
b10010100000001011010111010101100011111010101110 (
b10010100000001011010111010101100011111010101110 ,
1+
1&
#3025000
0&
#3031250
b10110 1
0+
1!
b10110 3
b0 4
1&
#3037500
0&
#3043750
0!
b1 4
1&
#3050000
0&
#3056250
1&
#3062500
0&
#3068750
1&
#3075000
0&
#3081250
1&
#3087500
0&
#3093750
1&
#3100000
0&
#3106250
1&
#3112500
0&
#3118750
1&
#3125000
0&
#3131250
1&
#3137500
0&
#3143750
1&
#3150000
0&
#3156250
b111010010001110111100111110001010111001011001111 (
b111010010001110111100111110001010111001011001111 ,
1+
1&
#3162500
0&
#3168750
b10111 1
0+
1!
b10111 3
b0 4
1&
#3175000
0&
#3181250
0!
b1 4
1&
#3187500
0&
#3193750
1&
#3200000
0&
#3206250
1&
#3212500
0&
#3218750
1&
#3225000
0&
#3231250
1&
#3237500
0&
#3243750
1&
#3250000
0&
#3256250
1&
#3262500
0&
#3268750
1&
#3275000
0&
#3281250
1&
#3287500
0&
#3293750
b10010010010001100000101000010010110010100001010 (
b10010010010001100000101000010010110010100001010 ,
1+
1&
#3300000
0&
#3306250
b11000 1
0+
1!
b11000 3
b0 4
1&
#3312500
0&
#3318750
0!
b1 4
1&
#3325000
0&
#3331250
1&
#3337500
0&
#3343750
1&
#3350000
0&
#3356250
1&
#3362500
0&
#3368750
1&
#3375000
0&
#3381250
1&
#3387500
0&
#3393750
1&
#3400000
0&
#3406250
1&
#3412500
0&
#3418750
1&
#3425000
0&
#3431250
b10101100101010011110001100010100110000111100 (
b10101100101010011110001100010100110000111100 ,
1+
1&
#3437500
0&
#3443750
b11001 1
0+
1!
b11001 3
b0 4
1&
#3450000
0&
#3456250
0!
b1 4
1&
#3462500
0&
#3468750
1&
#3475000
0&
#3481250
1&
#3487500
0&
#3493750
1&
#3500000
0&
#3506250
1&
#3512500
0&
#3518750
1&
#3525000
0&
#3531250
1&
#3537500
0&
#3543750
1&
#3550000
0&
#3556250
1&
#3562500
0&
#3568750
b101111011111001001000101001011100110000110001010 (
b101111011111001001000101001011100110000110001010 ,
1+
1&
#3575000
0&
#3581250
b11010 1
0+
1!
b11010 3
b0 4
1&
#3587500
0&
#3593750
0!
b1 4
1&
#3600000
0&
#3606250
1&
#3612500
0&
#3618750
1&
#3625000
0&
#3631250
1&
#3637500
0&
#3643750
1&
#3650000
0&
#3656250
1&
#3662500
0&
#3668750
1&
#3675000
0&
#3681250
1&
#3687500
0&
#3693750
1&
#3700000
0&
#3706250
b101100110100000111101100010010110011010011011000 (
b101100110100000111101100010010110011010011011000 ,
1+
1&
#3712500
0&
#3718750
b11011 1
0+
1!
b11011 3
b0 4
1&
#3725000
0&
#3731250
0!
b1 4
1&
#3737500
0&
#3743750
1&
#3750000
0&
#3756250
1&
#3762500
0&
#3768750
1&
#3775000
0&
#3781250
1&
#3787500
0&
#3793750
1&
#3800000
0&
#3806250
1&
#3812500
0&
#3818750
1&
#3825000
0&
#3831250
1&
#3837500
0&
#3843750
b111100110111100011000100100010100001001010001001 (
b111100110111100011000100100010100001001010001001 ,
1+
1&
#3850000
0&
#3856250
b11100 1
0+
1!
b11100 3
b0 4
1&
#3862500
0&
#3868750
0!
b1 4
1&
#3875000
0&
#3881250
1&
#3887500
0&
#3893750
1&
#3900000
0&
#3906250
1&
#3912500
0&
#3918750
1&
#3925000
0&
#3931250
1&
#3937500
0&
#3943750
1&
#3950000
0&
#3956250
1&
#3962500
0&
#3968750
1&
#3975000
0&
#3981250
b11011110101101011011000000100110010110110110 (
b11011110101101011011000000100110010110110110 ,
1+
1&
#3987500
0&
#3993750
b11101 1
0+
1!
b11101 3
b0 4
1&
#4000000
0&
#4006250
0!
b1 4
1&
#4012500
0&
#4018750
1&
#4025000
0&
#4031250
1&
#4037500
0&
#4043750
1&
#4050000
0&
#4056250
1&
#4062500
0&
#4068750
1&
#4075000
0&
#4081250
1&
#4087500
0&
#4093750
1&
#4100000
0&
#4106250
1&
#4112500
0&
#4118750
b111110011100011001010111000101010001001110101110 (
b111110011100011001010111000101010001001110101110 ,
1+
1&
#4125000
0&
#4131250
b11110 1
0+
1!
b11110 3
b0 4
1&
#4137500
0&
#4143750
0!
b1 4
1&
#4150000
0&
#4156250
1&
#4162500
0&
#4168750
1&
#4175000
0&
#4181250
1&
#4187500
0&
#4193750
1&
#4200000
0&
#4206250
1&
#4212500
0&
#4218750
1&
#4225000
0&
#4231250
1&
#4237500
0&
#4243750
1&
#4250000
0&
#4256250
b101011110000010101000011111101110100101010 (
b101011110000010101000011111101110100101010 ,
1+
1&
#4262500
0&
#4268750
b11111 1
0+
1!
b11111 3
b0 4
1&
#4275000
0&
#4281250
0!
b1 4
1&
#4287500
0&
#4293750
1&
#4300000
0&
#4306250
1&
#4312500
0&
#4318750
1&
#4325000
0&
#4331250
1&
#4337500
0&
#4343750
1&
#4350000
0&
#4356250
1&
#4362500
0&
#4368750
1&
#4375000
0&
#4381250
1&
#4387500
0&
#4393750
b100110100000101110111000100101111011111001110001 (
b100110100000101110111000100101111011111001110001 ,
1+
1&
#4400000
0&
#4406250
b100000 1
0+
1!
b100000 3
b0 4
1&
#4412500
0&
#4418750
0!
b1 4
1&
#4425000
0&
#4431250
1&
#4437500
0&
#4443750
1&
#4450000
0&
#4456250
1&
#4462500
0&
#4468750
1&
#4475000
0&
#4481250
1&
#4487500
0&
#4493750
1&
#4500000
0&
#4506250
1&
#4512500
0&
#4518750
1&
#4525000
0&
#4531250
b10000011000010100100111111100100101010101001111 (
b10000011000010100100111111100100101010101001111 ,
1+
1&
#4537500
0&
#4543750
b100001 1
0+
1!
b100001 3
b0 4
1&
#4550000
0&
#4556250
0!
b1 4
1&
#4562500
0&
#4568750
1&
#4575000
0&
#4581250
1&
#4587500
0&
